screen19/__init__.py
screen19/minimum_exposure.py
screen19/screen.py
screen19-0.213.dist-info/LICENSE
screen19-0.213.dist-info/METADATA
screen19-0.213.dist-info/WHEEL
screen19-0.213.dist-info/entry_points.txt
screen19-0.213.dist-info/top_level.txt
screen19-0.213.dist-info/RECORD
