Metadata-Version: 2.1
Name: screen19
Version: 0.213
Summary: Screening program for small-molecule single-crystal X-ray diffraction data
Home-page: UNKNOWN
Author: Diamond Light Source
Author-email: scientificsoftware@diamond.ac.uk
License: BSD license
Project-URL: Download, https://github.com/xia2/screen19/releases
Project-URL: GitHub, https://github.com/xia2/screen19
Project-URL: Bug-Tracker, https://github.com/xia2/screen19/issues
Platform: UNKNOWN
Classifier: Development Status :: 4 - Beta
Classifier: License :: OSI Approved :: BSD License
Classifier: Natural Language :: English
Classifier: Programming Language :: Python :: 3
Classifier: Programming Language :: Python :: 3.6
Classifier: Programming Language :: Python :: 3.7
Classifier: Programming Language :: Python :: 3.8
Classifier: Programming Language :: Python :: 3.9
Classifier: Operating System :: OS Independent
Requires-Python: >=3.6
License-File: LICENSE
